WinFreeze/__init__.py
WinFreeze-0.1.dist-info/METADATA
WinFreeze-0.1.dist-info/WHEEL
WinFreeze-0.1.dist-info/top_level.txt
WinFreeze-0.1.dist-info/RECORD
