Metadata-Version: 2.1
Name: WinFreeze
Version: 0.1
Summary: A simple Windows=based package used for freezing and unfreezing windows.
Author: pyProjects3 (github.com/pyProjects3)
License: MIT
Keywords: Windows,Microsoft,Freeze,Unfreeze,Processing,C++,Python3,Python
Classifier: Development Status :: 1 - Planning
Classifier: Intended Audience :: Developers
Classifier: Programming Language :: Python :: 3
Classifier: Operating System :: Microsoft :: Windows
Requires-Dist: pywin32
Requires-Dist: psutil
